agentics/__init__.py
agentics/core/__init__.py
agentics/core/agentics.py
agentics/core/async_executor.py
agentics/core/atype.py
agentics/core/default_types.py
agentics/core/llm_connections.py
agentics/core/mellea_pydantic_transducer.py
agentics/core/transducible_functions.py
agentics/core/utils.py
agentics/core/vector_store.py
agentics/ipython/__init__.py
agentics/scripts/__init__.py
agentics/scripts/show_llms.py
agentics_py-0.2.2.dist-info/METADATA
agentics_py-0.2.2.dist-info/WHEEL
agentics_py-0.2.2.dist-info/entry_points.txt
agentics_py-0.2.2.dist-info/licenses/LICENSE
agentics_py-0.2.2.dist-info/RECORD
