Metadata-Version: 2.4
Name: agentics-py
Version: 0.2.2
Summary: Agentics is a Python framework that provides structured, scalable, and semantically grounded agentic computation.
Author-email: Alfio Gliozzo <gliozzo@us.ibm.com>, Junkyu Lee <Junkyu.Lee@ibm.com>, Nahuel Defosse <nahuel.defosse@ibm.com>, Mustafa Eyceoz <Mustafa.Eyceoz@partner.ibm.com>, Naweed Aghmad Khan <naweed.khan@ibm.com>
License-Expression: Apache-2.0
License-File: LICENSE
Requires-Python: <3.13,>=3.11
Requires-Dist: aiosqlite>=0.21.0
Requires-Dist: async-lru>=2.0.5
Requires-Dist: crewai-tools[mcp]
Requires-Dist: crewai[google-genai]
Requires-Dist: crewai[tools]
Requires-Dist: datasets<5.0.0,>=4.0.0
Requires-Dist: ddgs
Requires-Dist: duckdb>=1.4.3
Requires-Dist: google<4.0.0,>=3.0.0
Requires-Dist: hnswlib>=0.8.0
Requires-Dist: ipywidgets>=8.1.7
Requires-Dist: json-schema-to-pydantic<0.4.0,>=0.3.0
Requires-Dist: jsonfinder
Requires-Dist: langchain-huggingface<0.3.0,>=0.2.0
Requires-Dist: litellm
Requires-Dist: loguru<0.8.0,>=0.7.3
Requires-Dist: mcp<2.0.0,>=1.13.1
Requires-Dist: mellea
Requires-Dist: numerize>=0.12
Requires-Dist: openai<2.0.0,>=1.88.0
Requires-Dist: openapi-python-client<0.25.0,>=0.24.3
Requires-Dist: pandas>=2.3.3
Requires-Dist: plotly>=6.5.0
Requires-Dist: pydantic
Requires-Dist: pyyaml<7.0.0,>=6.0.2
Requires-Dist: rich<14.0.0,>=13.0.0
Requires-Dist: streamlit<2.0.0,>=1.45.1
